{"name": "Polka Dot Plant", "scientific_name": "Hypoestes Phyllostachy", "sunlight_requirements": "indirect", "temperature_min": 0.0, "temperature_max": 40.0, "optimal_temperature_min": 15.0, "optimal_temperature_max": 26.0, "plant_distance_cm": 30, "ph_min": 6.0, "ph_max": 6.5, "watering_notes": ["Water when top 1-2cm of soil have dried out", "Only add little water at a time, better water more often"], "fertilizing_notes": ["Fertilize every 2-4 weeks during growth", "Reduce fertilizer during winter"], "pruning_notes": ["Remove Top leaves and blossoms to promote growth", "Cutting blossoms avoids dormancy"], "companions": ["Lemon bush", "Potato Vine"], "additional_notes": ["Mist regularly", "Goes dormant after blossoming", "New plants can be grown from cuttings"]}
